sainofirst/__init__.py
sainofirst/config.json
sainofirst/errors.json
sainofirst/services/sms/__init__.py
sainofirst/services/voice/__init__.py
sainofirst-1.0.2.dist-info/LICENSE
sainofirst-1.0.2.dist-info/METADATA
sainofirst-1.0.2.dist-info/WHEEL
sainofirst-1.0.2.dist-info/top_level.txt
sainofirst-1.0.2.dist-info/RECORD
