Metadata-Version: 2.1
Name: sainofirst
Version: 1.0.2
Summary: The Sainofirst SDK for python provides a python API for Sainofirst communication services.
Home-page: https://www.sainofirst.com
Author: Sainofirst
Author-email: contact@sainofirst.com
Maintainer: Shubz Kothekar
License: Apache
Project-URL: documentation, https://sainofirst.github.io/sainofirst-sdk-python
Project-URL: website, https://www.sainofirst.com
Project-URL: source, https://github.com/sainofirst/sainofirst-sdk-python
Project-URL: tracker, https://github.com/sainofirst/sainofirst-sdk-python/issues
Keywords: sdk bulk-sms bulk-voice sms-gateway voice-call
Platform: UNKNOWN
Classifier: Development Status :: 5 - Production/Stable
Classifier: Intended Audience :: Developers
Classifier: Natural Language :: English
Classifier: Programming Language :: Python :: 3
Classifier: Programming Language :: Python :: 3.2
Classifier: Programming Language :: Python :: 3.3
Classifier: Programming Language :: Python :: 3.4
Classifier: License :: OSI Approved :: Apache Software License
Requires-Python: >=3
Requires-Dist: requests (>=2)
